[
	{
		"CountryIsoAlpha2Code": "AU",
		"CountryIsoAlpha3Code": "AUS",
		"CountryName": "Australia",
		"InstitutionID": "041fb4c0-3e16-e711-9427-b8ca3a5db7a1",
		"OrganizationName": "Goora Gan Steiner School Inc.",
		"SubsectorCode": "education_k_12",
		"ProvinceCode": null,
		"AllowUnauthenticatedBrowsing": false,
		"FriendlyWebStoreUrl": null,
		"ProductMajorVersions": null,
		"WebStoreID": "47749cd3-3e16-e711-9427-b8ca3a5db7a1",
		"WebStoreName": "Goora Gan Steiner School Inc.",
		"WebStoreUrl": "https://e5.onthehub.com/WebStore/Welcome.aspx?ws=47749cd3-3e16-e711-9427-b8ca3a5db7a1"
	}
]