[
	{
		"CountryIsoAlpha2Code": "AU",
		"CountryIsoAlpha3Code": "AUS",
		"CountryName": "Australia",
		"InstitutionID": "3e120044-1763-e111-8056-f04da23e67f6",
		"OrganizationName": "Livingstone Christian College Ltd",
		"SubsectorCode": "education_k_12",
		"ProvinceCode": null,
		"AllowUnauthenticatedBrowsing": false,
		"FriendlyWebStoreUrl": "http://livingstone.qld.onthehub.com",
		"ProductMajorVersions": null,
		"WebStoreID": "c5c0efd9-1167-e111-ad7f-f04da23e67f6",
		"WebStoreName": "Livingstone Christian College Ltd",
		"WebStoreUrl": "https://e5.onthehub.com/WebStore/Welcome.aspx?ws=c5c0efd9-1167-e111-ad7f-f04da23e67f6"
	}
]